<annotation>
	<folder>metal</folder>
	<filename>IMG_20190427_192938.jpg</filename>
	<path>F:\Datasets Tese\Real\metal\IMG_20190427_192938.jpg</path>
	<source>
		<database>Unknown</database>
	</source>
	<size>
		<width>2610</width>
		<height>4640</height>
		<depth>3</depth>
	</size>
	<segmented>0</segmented>
	<object>
		<name>metal</name>
		<pose>Unspecified</pose>
		<truncated>0</truncated>
		<difficult>0</difficult>
		<bndbox>
			<xmin>410</xmin>
			<ymin>1215</ymin>
			<xmax>2465</xmax>
			<ymax>3430</ymax>
		</bndbox>
	</object>
</annotation>
